{
  "city": {
    "slug": "kyoto",
    "label": "京都"
  },
  "spots": [
    {
      "id": "hotel_kyoto",
      "city": "京都",
      "citySlug": "kyoto",
      "area": "京都站／東寺",
      "name": "LOISIR HOTEL KYOTO TOJI",
      "category": "住宿",
      "description": "京都前兩晚飯店。可作為京都抵達日休息點，也方便展開 Day 2 / Day 3 行程。",
      "sourceId": "github-fy26-kansai-data-kyoto",
      "sourceTitle": "GitHub repo・FY26 Kansai outing plan（京都資料匯入）",
      "sourceUrl": "https://github.com/coolbeardcool-lang/Fy26-travelplanning/blob/main/data.js",
      "bestTime": "晚上",
      "stayMinutes": 720,
      "tags": [
        "住宿",
        "飯店",
        "京都站",
        "東寺"
      ],
      "lat": 34.9777,
      "lng": 135.7514,
      "confidence": "已確認",
      "thumbnail": "🏨",
      "mapUrl": "https://www.google.com/maps?q=34.9777,135.7514",
      "published": true,
      "priorityScore": 72,
      "lastReviewedAt": "2026-04-03",
      "notes": "Imported from Fy26-travelplanning/data.js"
    },
    {
      "id": "kyoto_station",
      "city": "京都",
      "citySlug": "kyoto",
      "area": "京都站",
      "name": "京都站",
      "category": "交通樞紐",
      "description": "抵達日與京都市區散步的重要起點，晚上也可作為低強度備選行程。",
      "sourceId": "github-fy26-kansai-data-kyoto",
      "sourceTitle": "GitHub repo・FY26 Kansai outing plan（京都資料匯入）",
      "sourceUrl": "https://recommend.jr-central.co.jp/oshi-tabi/jujutanbo/",
      "bestTime": "下午",
      "stayMinutes": 30,
      "tags": [
        "京都站",
        "交通",
        "JJK",
        "夜景"
      ],
      "lat": 34.9858,
      "lng": 135.7581,
      "confidence": "已確認",
      "thumbnail": "🚉",
      "mapUrl": "https://www.google.com/maps?q=34.9858,135.7581",
      "published": true,
      "priorityScore": 78,
      "lastReviewedAt": "2026-04-03",
      "notes": "Imported from Fy26-travelplanning/data.js"
    },
    {
      "id": "kyoto_tower",
      "city": "京都",
      "citySlug": "kyoto",
      "area": "京都站",
      "name": "京都塔",
      "category": "景點",
      "description": "抵達日晚間可輕鬆補點的京都站周邊夜景地標。",
      "sourceId": "github-fy26-kansai-data-kyoto",
      "sourceTitle": "GitHub repo・FY26 Kansai outing plan（京都資料匯入）",
      "sourceUrl": "https://recommend.jr-central.co.jp/oshi-tabi/jujutanbo/",
      "bestTime": "晚上",
      "stayMinutes": 30,
      "tags": [
        "京都塔",
        "夜景",
        "地標"
      ],
      "lat": 34.9875,
      "lng": 135.7593,
      "confidence": "已確認",
      "thumbnail": "🗼",
      "mapUrl": "https://www.google.com/maps?q=34.9875,135.7593",
      "published": true,
      "priorityScore": 76,
      "lastReviewedAt": "2026-04-03",
      "notes": "Imported from Fy26-travelplanning/data.js"
    },
    {
      "id": "fushimi_inari",
      "city": "京都",
      "citySlug": "kyoto",
      "area": "伏見",
      "name": "伏見稻荷大社",
      "category": "寺社",
      "description": "京都經典代表景點，適合作為伏見區半日路線開場。",
      "sourceId": "github-fy26-kansai-data-kyoto",
      "sourceTitle": "GitHub repo・FY26 Kansai outing plan（京都資料匯入）",
      "sourceUrl": "https://recommend.jr-central.co.jp/oshi-tabi/jujutanbo/",
      "bestTime": "早上",
      "stayMinutes": 90,
      "tags": [
        "伏見稻荷",
        "千本鳥居",
        "寺社"
      ],
      "lat": 34.9671,
      "lng": 135.7727,
      "confidence": "已確認",
      "thumbnail": "⛩️",
      "mapUrl": "https://www.google.com/maps?q=34.9671,135.7727",
      "published": true,
      "priorityScore": 98,
      "lastReviewedAt": "2026-04-03",
      "notes": "Imported from Fy26-travelplanning/data.js"
    },
    {
      "id": "gokonomiya",
      "city": "京都",
      "citySlug": "kyoto",
      "area": "伏見",
      "name": "御香宮神社",
      "category": "寺社",
      "description": "伏見區的重要寺社點位，可與伏見稻荷串成同半日動線。",
      "sourceId": "github-fy26-kansai-data-kyoto",
      "sourceTitle": "GitHub repo・FY26 Kansai outing plan（京都資料匯入）",
      "sourceUrl": "https://github.com/coolbeardcool-lang/Fy26-travelplanning/blob/main/data.js",
      "bestTime": "下午",
      "stayMinutes": 30,
      "tags": [
        "神社",
        "伏見",
        "Pikmin"
      ],
      "lat": 34.9316,
      "lng": 135.7596,
      "confidence": "已確認",
      "thumbnail": "⛩️",
      "mapUrl": "https://www.google.com/maps?q=34.9316,135.7596",
      "published": true,
      "priorityScore": 74,
      "lastReviewedAt": "2026-04-03",
      "notes": "Imported from Fy26-travelplanning/data.js"
    },
    {
      "id": "zuishinin",
      "city": "京都",
      "citySlug": "kyoto",
      "area": "山科",
      "name": "隨心院",
      "category": "寺社",
      "description": "山科區寺社點位，接地鐵回河原町也相對順。",
      "sourceId": "github-fy26-kansai-data-kyoto",
      "sourceTitle": "GitHub repo・FY26 Kansai outing plan（京都資料匯入）",
      "sourceUrl": "https://github.com/coolbeardcool-lang/Fy26-travelplanning/blob/main/data.js",
      "bestTime": "下午",
      "stayMinutes": 45,
      "tags": [
        "山科",
        "寺社",
        "Pikmin"
      ],
      "lat": 34.9526,
      "lng": 135.814,
      "confidence": "已確認",
      "thumbnail": "⛩️",
      "mapUrl": "https://www.google.com/maps?q=34.9526,135.814",
      "published": true,
      "priorityScore": 72,
      "lastReviewedAt": "2026-04-03",
      "notes": "Imported from Fy26-travelplanning/data.js"
    },
    {
      "id": "kamo_bridge",
      "city": "京都",
      "citySlug": "kyoto",
      "area": "四條河原町",
      "name": "鴨川四條大橋",
      "category": "散步",
      "description": "很適合放慢節奏的城市散步點，可銜接河原町晚餐與逛街。",
      "sourceId": "github-fy26-kansai-data-kyoto",
      "sourceTitle": "GitHub repo・FY26 Kansai outing plan（京都資料匯入）",
      "sourceUrl": "https://recommend.jr-central.co.jp/oshi-tabi/jujutanbo/",
      "bestTime": "傍晚",
      "stayMinutes": 30,
      "tags": [
        "鴨川",
        "散步",
        "河原町"
      ],
      "lat": 35.0036,
      "lng": 135.7697,
      "confidence": "已確認",
      "thumbnail": "🌉",
      "mapUrl": "https://www.google.com/maps?q=35.0036,135.7697",
      "published": true,
      "priorityScore": 84,
      "lastReviewedAt": "2026-04-03",
      "notes": "Imported from Fy26-travelplanning/data.js"
    },
    {
      "id": "kiddy_land",
      "city": "京都",
      "citySlug": "kyoto",
      "area": "四條河原町",
      "name": "KIDDY LAND 京都四條河原町店",
      "category": "逛街",
      "description": "動漫周邊與角色商品集中，接錦市場和河原町晚餐最順。",
      "sourceId": "github-fy26-kansai-data-kyoto",
      "sourceTitle": "GitHub repo・FY26 Kansai outing plan（京都資料匯入）",
      "sourceUrl": "https://recommend.jr-central.co.jp/oshi-tabi/jujutanbo/",
      "bestTime": "下午",
      "stayMinutes": 40,
      "tags": [
        "動漫",
        "購物",
        "河原町"
      ],
      "lat": 35.0057,
      "lng": 135.7681,
      "confidence": "已確認",
      "thumbnail": "🛍️",
      "mapUrl": "https://www.google.com/maps?q=35.0057,135.7681",
      "published": true,
      "priorityScore": 75,
      "lastReviewedAt": "2026-04-03",
      "notes": "Imported from Fy26-travelplanning/data.js"
    },
    {
      "id": "yasaka_pagoda",
      "city": "京都",
      "citySlug": "kyoto",
      "area": "東山",
      "name": "八坂塔（法觀寺）",
      "category": "景點",
      "description": "京都街景辨識度極高的地標，拍照與散步都很適合。",
      "sourceId": "github-fy26-kansai-data-kyoto",
      "sourceTitle": "GitHub repo・FY26 Kansai outing plan（京都資料匯入）",
      "sourceUrl": "https://recommend.jr-central.co.jp/oshi-tabi/jujutanbo/",
      "bestTime": "下午",
      "stayMinutes": 30,
      "tags": [
        "東山",
        "八坂塔",
        "拍照"
      ],
      "lat": 34.9968,
      "lng": 135.7809,
      "confidence": "已確認",
      "thumbnail": "🏯",
      "mapUrl": "https://www.google.com/maps?q=34.9968,135.7809",
      "published": true,
      "priorityScore": 90,
      "lastReviewedAt": "2026-04-03",
      "notes": "Imported from Fy26-travelplanning/data.js"
    },
    {
      "id": "yasaka_shrine",
      "city": "京都",
      "citySlug": "kyoto",
      "area": "祇園／東山",
      "name": "八坂神社",
      "category": "寺社",
      "description": "祇園代表寺社點位，可併入東山散步段。",
      "sourceId": "github-fy26-kansai-data-kyoto",
      "sourceTitle": "GitHub repo・FY26 Kansai outing plan（京都資料匯入）",
      "sourceUrl": "https://enjoy-osaka-kyoto-kobe.com/zh-Hant/article/a/conan-kyoto/",
      "bestTime": "下午",
      "stayMinutes": 30,
      "tags": [
        "祇園",
        "東山",
        "神社"
      ],
      "lat": 35.0037,
      "lng": 135.7788,
      "confidence": "已確認",
      "thumbnail": "⛩️",
      "mapUrl": "https://www.google.com/maps?q=35.0037,135.7788",
      "published": true,
      "priorityScore": 88,
      "lastReviewedAt": "2026-04-03",
      "notes": "Imported from Fy26-travelplanning/data.js"
    },
    {
      "id": "kiyomizu",
      "city": "京都",
      "citySlug": "kyoto",
      "area": "東山",
      "name": "清水寺",
      "category": "寺社",
      "description": "京都代表級寺社景點，可自八坂塔一路延伸過去。",
      "sourceId": "github-fy26-kansai-data-kyoto",
      "sourceTitle": "GitHub repo・FY26 Kansai outing plan（京都資料匯入）",
      "sourceUrl": "https://enjoy-osaka-kyoto-kobe.com/zh-Hant/article/a/conan-kyoto/",
      "bestTime": "早上",
      "stayMinutes": 90,
      "tags": [
        "清水寺",
        "東山",
        "京都經典"
      ],
      "lat": 34.9949,
      "lng": 135.7851,
      "confidence": "已確認",
      "thumbnail": "⛩️",
      "mapUrl": "https://www.google.com/maps?q=34.9949,135.7851",
      "published": true,
      "priorityScore": 97,
      "lastReviewedAt": "2026-04-03",
      "notes": "Imported from Fy26-travelplanning/data.js"
    },
    {
      "id": "yasaka_koshindo",
      "city": "京都",
      "citySlug": "kyoto",
      "area": "東山",
      "name": "八坂庚申堂",
      "category": "寺社",
      "description": "與八坂塔幾乎屬同一段散步路線，拍照感很強。",
      "sourceId": "github-fy26-kansai-data-kyoto",
      "sourceTitle": "GitHub repo・FY26 Kansai outing plan（京都資料匯入）",
      "sourceUrl": "https://enjoy-osaka-kyoto-kobe.com/zh-Hant/article/a/conan-kyoto/",
      "bestTime": "下午",
      "stayMinutes": 20,
      "tags": [
        "東山",
        "拍照",
        "寺社"
      ],
      "lat": 34.9967,
      "lng": 135.7813,
      "confidence": "已確認",
      "thumbnail": "🎐",
      "mapUrl": "https://www.google.com/maps?q=34.9967,135.7813",
      "published": true,
      "priorityScore": 79,
      "lastReviewedAt": "2026-04-03",
      "notes": "Imported from Fy26-travelplanning/data.js"
    },
    {
      "id": "pontocho",
      "city": "京都",
      "citySlug": "kyoto",
      "area": "河原町／鴨川側",
      "name": "先斗町",
      "category": "散步",
      "description": "很適合排晚餐後散步的京都經典街區。",
      "sourceId": "github-fy26-kansai-data-kyoto",
      "sourceTitle": "GitHub repo・FY26 Kansai outing plan（京都資料匯入）",
      "sourceUrl": "https://enjoy-osaka-kyoto-kobe.com/zh-Hant/article/a/conan-kyoto/",
      "bestTime": "晚上",
      "stayMinutes": 45,
      "tags": [
        "先斗町",
        "鴨川",
        "夜晚散步"
      ],
      "lat": 35.006,
      "lng": 135.7704,
      "confidence": "已確認",
      "thumbnail": "🏮",
      "mapUrl": "https://www.google.com/maps?q=35.006,135.7704",
      "published": true,
      "priorityScore": 86,
      "lastReviewedAt": "2026-04-03",
      "notes": "Imported from Fy26-travelplanning/data.js"
    },
    {
      "id": "nishiki",
      "city": "京都",
      "citySlug": "kyoto",
      "area": "四條／錦市場",
      "name": "錦市場（小吃區）",
      "category": "小吃",
      "description": "京都市中心補小吃最方便的市場區，適合停下來慢慢吃。",
      "sourceId": "github-fy26-kansai-data-kyoto",
      "sourceTitle": "GitHub repo・FY26 Kansai outing plan（京都資料匯入）",
      "sourceUrl": "https://github.com/coolbeardcool-lang/Fy26-travelplanning/blob/main/data.js",
      "bestTime": "中午",
      "stayMinutes": 75,
      "tags": [
        "錦市場",
        "小吃",
        "市場"
      ],
      "lat": 35.005,
      "lng": 135.7642,
      "confidence": "已確認",
      "thumbnail": "🍡",
      "mapUrl": "https://www.google.com/maps?q=35.005,135.7642",
      "published": true,
      "priorityScore": 92,
      "lastReviewedAt": "2026-04-03",
      "notes": "Imported from Fy26-travelplanning/data.js"
    },
    {
      "id": "inoichi",
      "city": "京都",
      "citySlug": "kyoto",
      "area": "河原町",
      "name": "麵屋豬一",
      "category": "餐廳",
      "description": "京都市中心正餐候選，適合安排在河原町路線中。",
      "sourceId": "github-fy26-kansai-data-kyoto",
      "sourceTitle": "GitHub repo・FY26 Kansai outing plan（京都資料匯入）",
      "sourceUrl": "https://github.com/coolbeardcool-lang/Fy26-travelplanning/blob/main/data.js",
      "bestTime": "中午",
      "stayMinutes": 60,
      "tags": [
        "拉麵",
        "河原町",
        "正餐"
      ],
      "lat": 35.0015,
      "lng": 135.7675,
      "confidence": "已確認",
      "thumbnail": "🍜",
      "mapUrl": "https://www.google.com/maps?q=35.0015,135.7675",
      "published": true,
      "priorityScore": 83,
      "lastReviewedAt": "2026-04-03",
      "notes": "Imported from Fy26-travelplanning/data.js"
    },
    {
      "id": "hitsuji",
      "city": "京都",
      "citySlug": "kyoto",
      "area": "丸太町",
      "name": "Hitsuji",
      "category": "甜點",
      "description": "適合有餘裕時補進去的甜點點位。",
      "sourceId": "github-fy26-kansai-data-kyoto",
      "sourceTitle": "GitHub repo・FY26 Kansai outing plan（京都資料匯入）",
      "sourceUrl": "https://github.com/coolbeardcool-lang/Fy26-travelplanning/blob/main/data.js",
      "bestTime": "下午",
      "stayMinutes": 40,
      "tags": [
        "甜點",
        "丸太町"
      ],
      "lat": 35.0149,
      "lng": 135.7658,
      "confidence": "已確認",
      "thumbnail": "🍰",
      "mapUrl": "https://www.google.com/maps?q=35.0149,135.7658",
      "published": true,
      "priorityScore": 68,
      "lastReviewedAt": "2026-04-03",
      "notes": "Imported from Fy26-travelplanning/data.js"
    },
    {
      "id": "campo",
      "city": "京都",
      "citySlug": "kyoto",
      "area": "丸太町／烏丸御池",
      "name": "CAMPO su OVEST",
      "category": "餐廳",
      "description": "想把某天收得更完整時，可安排的晚餐點。",
      "sourceId": "github-fy26-kansai-data-kyoto",
      "sourceTitle": "GitHub repo・FY26 Kansai outing plan（京都資料匯入）",
      "sourceUrl": "https://github.com/coolbeardcool-lang/Fy26-travelplanning/blob/main/data.js",
      "bestTime": "晚上",
      "stayMinutes": 120,
      "tags": [
        "晚餐",
        "義式",
        "烏丸御池"
      ],
      "lat": 35.0166,
      "lng": 135.7587,
      "confidence": "已確認",
      "thumbnail": "🍽️",
      "mapUrl": "https://www.google.com/maps?q=35.0166,135.7587",
      "published": true,
      "priorityScore": 71,
      "lastReviewedAt": "2026-04-03",
      "notes": "Imported from Fy26-travelplanning/data.js"
    },
    {
      "id": "rakusai_bamboo",
      "city": "京都",
      "citySlug": "kyoto",
      "area": "西京",
      "name": "京都市洛西竹林公園",
      "category": "景點",
      "description": "散步感輕鬆的竹林點位，適合排在西京／嵐山半日路線。",
      "sourceId": "github-fy26-kansai-data-kyoto",
      "sourceTitle": "GitHub repo・FY26 Kansai outing plan（京都資料匯入）",
      "sourceUrl": "https://github.com/coolbeardcool-lang/Fy26-travelplanning/blob/main/data.js",
      "bestTime": "早上",
      "stayMinutes": 45,
      "tags": [
        "竹林",
        "西京",
        "散步"
      ],
      "lat": 34.9664,
      "lng": 135.6737,
      "confidence": "已確認",
      "thumbnail": "🎋",
      "mapUrl": "https://www.google.com/maps?q=34.9664,135.6737",
      "published": true,
      "priorityScore": 77,
      "lastReviewedAt": "2026-04-03",
      "notes": "Imported from Fy26-travelplanning/data.js"
    },
    {
      "id": "rakushisha",
      "city": "京都",
      "citySlug": "kyoto",
      "area": "嵯峨・嵐山",
      "name": "落柿舍",
      "category": "景點",
      "description": "文學氣息濃厚，適合平衡跑點節奏。",
      "sourceId": "github-fy26-kansai-data-kyoto",
      "sourceTitle": "GitHub repo・FY26 Kansai outing plan（京都資料匯入）",
      "sourceUrl": "https://github.com/coolbeardcool-lang/Fy26-travelplanning/blob/main/data.js",
      "bestTime": "下午",
      "stayMinutes": 40,
      "tags": [
        "文學",
        "嵐山",
        "散步"
      ],
      "lat": 35.0243,
      "lng": 135.6769,
      "confidence": "已確認",
      "thumbnail": "📚",
      "mapUrl": "https://www.google.com/maps?q=35.0243,135.6769",
      "published": true,
      "priorityScore": 73,
      "lastReviewedAt": "2026-04-03",
      "notes": "Imported from Fy26-travelplanning/data.js"
    },
    {
      "id": "togetsukyo",
      "city": "京都",
      "citySlug": "kyoto",
      "area": "嵐山",
      "name": "渡月橋",
      "category": "景點",
      "description": "嵐山代表景，適合搭配竹林與周邊散步。",
      "sourceId": "github-fy26-kansai-data-kyoto",
      "sourceTitle": "GitHub repo・FY26 Kansai outing plan（京都資料匯入）",
      "sourceUrl": "https://matcha-jp.com/tw/7826",
      "bestTime": "下午",
      "stayMinutes": 40,
      "tags": [
        "嵐山",
        "渡月橋",
        "拍照"
      ],
      "lat": 35.0139,
      "lng": 135.6779,
      "confidence": "已確認",
      "thumbnail": "🌉",
      "mapUrl": "https://www.google.com/maps?q=35.0139,135.6779",
      "published": true,
      "priorityScore": 91,
      "lastReviewedAt": "2026-04-03",
      "notes": "Imported from Fy26-travelplanning/data.js"
    },
    {
      "id": "jingoji",
      "city": "京都",
      "citySlug": "kyoto",
      "area": "高雄",
      "name": "神護寺",
      "category": "寺社",
      "description": "高雄山景段的主點，適合安排作為後段收尾。",
      "sourceId": "github-fy26-kansai-data-kyoto",
      "sourceTitle": "GitHub repo・FY26 Kansai outing plan（京都資料匯入）",
      "sourceUrl": "https://github.com/coolbeardcool-lang/Fy26-travelplanning/blob/main/data.js",
      "bestTime": "下午",
      "stayMinutes": 75,
      "tags": [
        "高雄",
        "寺社",
        "山景"
      ],
      "lat": 35.0606,
      "lng": 135.6702,
      "confidence": "已確認",
      "thumbnail": "⛰️",
      "mapUrl": "https://www.google.com/maps?q=35.0606,135.6702",
      "published": true,
      "priorityScore": 74,
      "lastReviewedAt": "2026-04-03",
      "notes": "Imported from Fy26-travelplanning/data.js"
    },
    {
      "id": "philosophers_path",
      "city": "京都",
      "citySlug": "kyoto",
      "area": "左京",
      "name": "哲學之道",
      "category": "散步",
      "description": "經典文學散步補線，適合想把京都走得更詩意時加入。",
      "sourceId": "github-fy26-kansai-data-kyoto",
      "sourceTitle": "GitHub repo・FY26 Kansai outing plan（京都資料匯入）",
      "sourceUrl": "https://github.com/coolbeardcool-lang/Fy26-travelplanning/blob/main/data.js",
      "bestTime": "下午",
      "stayMinutes": 75,
      "tags": [
        "左京",
        "散步",
        "文學"
      ],
      "lat": 35.0198,
      "lng": 135.7952,
      "confidence": "已確認",
      "thumbnail": "🚶",
      "mapUrl": "https://www.google.com/maps?q=35.0198,135.7952",
      "published": true,
      "priorityScore": 85,
      "lastReviewedAt": "2026-04-03",
      "notes": "Imported from Fy26-travelplanning/data.js"
    },
    {
      "id": "monk",
      "city": "京都",
      "citySlug": "kyoto",
      "area": "哲學之道",
      "name": "Monk",
      "category": "餐廳",
      "description": "哲學之道周邊的預約餐廳，可作為 Day 3 升級版收尾。",
      "sourceId": "github-fy26-kansai-data-kyoto",
      "sourceTitle": "GitHub repo・FY26 Kansai outing plan（京都資料匯入）",
      "sourceUrl": "https://github.com/coolbeardcool-lang/Fy26-travelplanning/blob/main/data.js",
      "bestTime": "晚上",
      "stayMinutes": 150,
      "tags": [
        "預約制",
        "餐廳",
        "哲學之道"
      ],
      "lat": 35.0231,
      "lng": 135.7962,
      "confidence": "已確認",
      "thumbnail": "🍽️",
      "mapUrl": "https://www.google.com/maps?q=35.0231,135.7962",
      "published": true,
      "priorityScore": 72,
      "lastReviewedAt": "2026-04-03",
      "notes": "Imported from Fy26-travelplanning/data.js"
    }
  ],
  "events": [],
  "sources": [
    {
      "id": "github-fy26-kansai-data-kyoto",
      "title": "GitHub repo・FY26 Kansai outing plan（京都資料匯入）",
      "url": "https://github.com/coolbeardcool-lang/Fy26-travelplanning/blob/main/data.js",
      "platform": "GitHub",
      "sourceType": "行程資料",
      "status": "已匯入",
      "note": "由 Fy26-travelplanning repo 的 data.js 匯入京都點位，保留原始路線規劃中的景點、餐廳、散步點與住宿節點。"
    }
  ],
  "meta": {
    "importedFrom": "coolbeardcool-lang/Fy26-travelplanning",
    "path": "data.js",
    "count": 23
  }
}